{
  "users": [
    {
      "id": 1,
      "email": "test@test.com",
      "password": "1234",
      "name": "Alice"
    },
    {
      "id": 2,
      "email": "test2@test.com",
      "password": "12345",
      "name": "Alexandra"
    }
  ],
  "cart": [
    {
      "bookId": "9781098112042",
      "count": 1,
      "userId": 1,
      "id": 1
    },
    {
      "bookId": "9781098113087",
      "count": 1,
      "userId": 1,
      "id": 2
    },
    {
      "bookId": "9781098118808",
      "count": 1,
      "userId": 1,
      "id": 4
    },
    {
      "bookId": "9781098112042",
      "count": 1,
      "userId": 2,
      "id": 5
    },
    {
      "bookId": "9781098130923",
      "count": 1,
      "userId": 1,
      "id": 6
    },
    {
      "bookId": "9781098103828",
      "count": 1,
      "userId": 1,
      "id": 7
    },
    {
      "bookId": "9781098103828",
      "count": 1,
      "userId": 1,
      "id": 8
    },
    {
      "bookId": "9781098104030",
      "count": 1,
      "userId": 1,
      "id": 9
    },
    {
      "bookId": "9781098106225",
      "count": 1,
      "userId": 1,
      "id": 10
    },
    {
      "bookId": "9781098112844",
      "count": 1,
      "userId": 1,
      "id": 11
    },
    {
      "bookId": "9781098111878",
      "count": 1,
      "userId": 1,
      "id": 12
    },
    {
      "bookId": "9780596003968",
      "count": 1,
      "userId": 1,
      "id": 13
    },
    {
      "bookId": "9781430225270",
      "count": 1,
      "userId": 1,
      "id": 14
    },
    {
      "bookId": "9781430247401",
      "count": 1,
      "userId": 1,
      "id": 15
    },
    {
      "count": 2,
      "id": 16
    },
    {
      "bookId": "9781430247401",
      "count": 2,
      "userId": 1,
      "id": 17
    },
    {
      "bookId": "9781430231356",
      "count": 3,
      "userId": 1,
      "id": 18
    },
    {
      "bookId": "9781484211830",
      "count": 1,
      "userId": 1,
      "id": 19
    },
    {
      "bookId": "9781430241010",
      "count": 1,
      "userId": 1,
      "id": 20
    },
    {
      "bookId": "9781430224396",
      "count": 1,
      "userId": 1,
      "id": 21
    },
    {
      "bookId": "9781430268215",
      "count": 1,
      "userId": 1,
      "id": 22
    },
    {
      "bookId": "9781484233863",
      "count": 1,
      "userId": 1,
      "id": 23
    },
    {
      "bookId": "9781484233863",
      "count": 1,
      "userId": 1,
      "id": 24
    },
    {
      "bookId": "9781430240143",
      "count": 1,
      "userId": 1,
      "id": 25
    },
    {
      "bookId": "9781484233894",
      "count": 1,
      "userId": 1,
      "id": 26
    },
    {
      "bookId": "9781430230908",
      "count": 1,
      "userId": 1,
      "id": 27
    },
    {
      "bookId": "9781430230908",
      "count": 1,
      "userId": 1,
      "id": 28
    },
    {
      "bookId": "9781118530801",
      "count": 1,
      "userId": 1,
      "id": 29
    },
    {
      "bookId": "9781098103828",
      "count": 1,
      "userId": 1,
      "id": 30
    },
    {
      "bookId": "9781098116743",
      "count": 1,
      "userId": 1,
      "id": 31
    },
    {
      "bookId": "9780596804046",
      "count": 1,
      "userId": 1,
      "id": 32
    },
    {
      "bookId": "9781783987481",
      "count": 1,
      "userId": 1,
      "id": 33
    },
    {
      "bookId": "9781788622448",
      "count": 1,
      "userId": 1,
      "id": 34
    }
  ],
  "wishlist": [
    {
      "userId": 1,
      "count": 0,
      "books": []
    },
    {
      "userId": 2,
      "count": 0,
      "books": []
    }
  ]
}